bigquery_sql_parser/__init__.py
bigquery_sql_parser/column.py
bigquery_sql_parser/cte.py
bigquery_sql_parser/line.py
bigquery_sql_parser/multiline.py
bigquery_sql_parser/query.py
bigquery_sql_parser/script.py
bigquery_sql_parser/tokenizer.py
bigquery_sql_parser/utils.py
bigquery_sql_parser-0.1.4.dist-info/LICENSE
bigquery_sql_parser-0.1.4.dist-info/METADATA
bigquery_sql_parser-0.1.4.dist-info/WHEEL
bigquery_sql_parser-0.1.4.dist-info/top_level.txt
bigquery_sql_parser-0.1.4.dist-info/RECORD
