Metadata-Version: 2.1
Name: bigquery-sql-parser
Version: 0.1.4
Summary: Simple and out of the box Bigquery SQL Parser for python. Convert your SQL into python object which you can modify programatically.
Home-page: https://github.com/maztohir/bigquery-sql-parser
Author: Muhamad Tohir
Author-email: maztohir@gmail.com
License: UNKNOWN
Project-URL: Bug Tracker, https://github.com/maztohir/bigquery-sql-parser/issues
Platform: UNKNOWN
Classifier: Programming Language :: Python :: 3
Classifier: License :: OSI Approved :: MIT License
Classifier: Operating System :: OS Independent
Requires-Python: >=3.6
